{
  "$schema": "https://mintlify.com/docs.json",
  "theme": "mint",
  "name": "Zappl Documentation.",
  "colors": {
    "primary": "#117DF8",
    "light": "#117DF8",
    "dark": "#117DF8"
  },
  "favicon": "/favicon.svg",
  "navigation": {
    "tabs": [
      {
        "tab": "Guides",
        "groups": [
          {
            "group": "About Zappl",
            "pages": [
              "about/introduction",
              "about/requirements",
              "about/security",
              "about/macOS-components",
              "about/FAQ"
            ]
          },
          {
            "group": "Deploying Zappl",
            "pages": [
              "deploy/general",
              "deploy/jamf-pro",
              "deploy/jamf-school",
              "deploy/kandji",
              "deploy/intune",
              "deploy/other-mdm"
            ]
          },
          {
            "group": "Customisation",
            "pages": [
              "customise/preferences",
              "customise/message-variables"
            ]
          },
          {
            "group": "Applications",
            "pages": [
              "apps/updates",
              "apps/installs"
            ]
          },
          {
            "group": "Online Portal",
            "pages": [
              "portal/accounts",
              "portal/dashboard",
              "portal/devices",
              "portal/device-records",
              "portal/applications",
              "portal/reports",
              "portal/settings"
            ]
          },
          {
            "group": "Other",
            "pages": [
              "other/command-line",
              "other/logs-errors",
              "other/troubleshooting",
              "other/uninstall"
            ]
          }
        ]
      },
      {
        "tab": "API Reference",
        "groups": [
          {
            "group": "API Documentation",
            "pages": [
              "api-reference/introduction"
            ]
          },
          {
            "group": "Endpoint Examples",
            "pages": [
              "api-reference/endpoint/get",
              "api-reference/endpoint/create",
              "api-reference/endpoint/delete",
              "api-reference/endpoint/webhook"
            ]
          }
        ]
      }
    ],
    "global": {
      "anchors": [
        {
          "anchor": "zappl.co",
          "href": "https://zappl.co",
          "icon": "location-pin"
        },
        {
          "anchor": "dare.tech",
          "href": "https://dare.tech",
          "icon": "location-pin"

        }
      ]
    }
  },
  "logo": {
    "light": "/logo/zappl_logo.svg",
    "dark": "/logo/dark.svg"
  },
  "navbar": {
    "links": [
      {
        "label": "Zappl Support",
        "href": "mailto:helpdesk@dare.tech"
      }
    ],
    "primary": {
      "type": "button",
      "label": "Zappl Portal",
      "href": "https://portal.zappl.co"
    }
  },
  "footer": {
    "socials": {
      "github": "https://github.com/dare-tech",
      "linkedin": "https://www.linkedin.com/company/dare-technology-ltd"
    }
  }
}